buildrule/__init__.py
buildrule/rule_node.py
buildrule/rule/__init__.py
buildrule/rule/boolean_rules/__init__.py
buildrule/rule/boolean_rules/core.py
buildrule/rule/datetime_rules/__init__.py
buildrule/rule/datetime_rules/core.py
buildrule/rule/dict_ext_rules/__init__.py
buildrule/rule/dict_ext_rules/core.py
buildrule/rule/list_rules/__init__.py
buildrule/rule/list_rules/core.py
buildrule/rule/numeric_rules/__init__.py
buildrule/rule/numeric_rules/core.py
buildrule/rule/regex_rules/__init__.py
buildrule/rule/regex_rules/core.py
buildrule/rule/set_rules/__init__.py
buildrule/rule/set_rules/core.py
buildrule/rule/string_rules/__init__.py
buildrule/rule/string_rules/core.py
buildrule/rule/xml_rules/__init__.py
buildrule/rule/xml_rules/core.py
buildrule-0.0.2.dist-info/licenses/LICENSE
buildrule-0.0.2.dist-info/METADATA
buildrule-0.0.2.dist-info/WHEEL
buildrule-0.0.2.dist-info/top_level.txt
buildrule-0.0.2.dist-info/RECORD
